llmperf/__init__.py
llmperf/main.py
llmperf-0.0.1.dist-info/METADATA
llmperf-0.0.1.dist-info/WHEEL
llmperf-0.0.1.dist-info/entry_points.txt
llmperf-0.0.1.dist-info/top_level.txt
llmperf-0.0.1.dist-info/RECORD
